scco2.py
scco2-0.0.3.dist-info/METADATA
scco2-0.0.3.dist-info/WHEEL
scco2-0.0.3.dist-info/entry_points.txt
scco2-0.0.3.dist-info/top_level.txt
scco2-0.0.3.dist-info/RECORD
