Metadata-Version: 2.1
Name: scco2
Version: 0.0.3
Summary: A package for visualizing the relationship between CO2 emissions and population in a specified country
Home-page: https://github.com/YamanoRyosuke/scco2.py
Author: ryosuke yamano
Author-email: s2022035@stu.musashino-u.ac.jp
License: UNKNOWN
Project-URL: Bug Tracker, https://github.com/YamanoRyosuke/scco2.py
Platform: UNKNOWN
Classifier: Programming Language :: Python :: 3
Classifier: License :: OSI Approved :: MIT License
Classifier: Operating System :: OS Independent
Requires-Python: >=3.8
